odoo/addons/sale_order_line_view_negative_margin/README.rst
odoo/addons/sale_order_line_view_negative_margin/__init__.py
odoo/addons/sale_order_line_view_negative_margin/__manifest__.py
odoo/addons/sale_order_line_view_negative_margin/models/__init__.py
odoo/addons/sale_order_line_view_negative_margin/models/sale_order_line.py
odoo/addons/sale_order_line_view_negative_margin/static/description/icon.png
odoo/addons/sale_order_line_view_negative_margin/views/sale_order_views.xml
odoo_addon_sale_order_line_view_negative_margin-16.0.1.0.0.2.dist-info/METADATA
odoo_addon_sale_order_line_view_negative_margin-16.0.1.0.0.2.dist-info/WHEEL
odoo_addon_sale_order_line_view_negative_margin-16.0.1.0.0.2.dist-info/top_level.txt
odoo_addon_sale_order_line_view_negative_margin-16.0.1.0.0.2.dist-info/RECORD
