Metadata-Version: 2.1
Name: odoo-addon-sale_order_line_view_negative_margin
Version: 16.0.1.0.0.2
Requires-Python: >=3.10
Requires-Dist: odoo>=16.0a,<16.1dev
Summary: Sale Order Line turns red if margin is negative or 0
Home-page: https://github.com/sygel-technology/sy-sale-workflow
License: AGPL-3
Author: Sygel
Classifier: Programming Language :: Python
Classifier: Framework :: Odoo
Classifier: Framework :: Odoo :: 16.0
Classifier: License :: OSI Approved :: GNU Affero General Public License v3
